pytelechat/__init__.py
pytelechat/chatdata.py
pytelechat/errors.py
pytelechat-0.1.0.dist-info/LICENSE
pytelechat-0.1.0.dist-info/METADATA
pytelechat-0.1.0.dist-info/WHEEL
pytelechat-0.1.0.dist-info/top_level.txt
pytelechat-0.1.0.dist-info/RECORD
